chronically_needs_csv/__init__.py
chronically_needs_csv/__main__.py
chronically_needs_csv-0.0.2.dist-info/METADATA
chronically_needs_csv-0.0.2.dist-info/WHEEL
chronically_needs_csv-0.0.2.dist-info/entry_points.txt
chronically_needs_csv-0.0.2.dist-info/licenses/LICENSE
chronically_needs_csv-0.0.2.dist-info/RECORD
