Metadata-Version: 2.4
Name: chronically-needs-csv
Version: 0.0.2
Summary: A JSON to CSV converter for analysts who chronically can't parse JSON themselves.
Project-URL: Repository, https://github.com/JellevanE/chronically-needs-csv
Project-URL: Issues, https://github.com/JellevanE/chronically-needs-csv/issues
Author: A tired friend
License-Expression: MIT
License-File: LICENSE
Keywords: analyst,chronis,converter,csv,json
Classifier: Development Status :: 4 - Beta
Classifier: Intended Audience :: Developers
Classifier: Intended Audience :: Science/Research
Classifier: License :: OSI Approved :: MIT License
Classifier: Programming Language :: Python :: 3.10
Classifier: Programming Language :: Python :: 3.11
Classifier: Programming Language :: Python :: 3.12
Classifier: Topic :: Text Processing :: General
Classifier: Topic :: Utilities
Requires-Python: >=3.10
